{ "compressionlevel":-1,
 "editorsettings":
    {
     "export":
        {
         "target":"."
        }
    },
 "height":15,
 "infinite":false,
 "layers":[
        {
         "draworder":"topdown",
         "id":2,
         "name":"objects",
         "objects":[
                {
                 "gid":422,
                 "height":46,
                 "id":106,
                 "name":"",
                 "rotation":0,
                 "type":"ironCar",
                 "visible":true,
                 "width":100,
                 "x":710.773098390147,
                 "y":465.878638313575
                }, 
                {
                 "height":41.2847456063471,
                 "id":80,
                 "name":"",
                 "rotation":0,
                 "type":"lava",
                 "visible":true,
                 "width":672.029152636192,
                 "x":-9.34305087873071,
                 "y":451.581469009949
                }, 
                {
                 "height":22,
                 "id":1,
                 "name":"",
                 "rotation":0,
                 "type":"wall",
                 "visible":true,
                 "width":102.985316050864,
                 "x":16.6472315758723,
                 "y":397.260113473869
                }, 
                {
                 "height":420.020111628765,
                 "id":4,
                 "name":"",
                 "rotation":0,
                 "type":"wall",
                 "visible":true,
                 "width":24,
                 "x":7.40135615111398,
                 "y":2.71005735196884
                }, 
                {
                 "height":18.6666666666667,
                 "id":5,
                 "name":"",
                 "rotation":0,
                 "type":"wall",
                 "visible":true,
                 "width":236,
                 "x":233.333333333333,
                 "y":265.333333333333
                }, 
                {
                 "height":353.333333333333,
                 "id":7,
                 "name":"",
                 "rotation":0,
                 "type":"wall",
                 "visible":true,
                 "width":24,
                 "x":572.058305272383,
                 "y":-181.363162507496
                }, 
                {
                 "height":28,
                 "id":12,
                 "name":"",
                 "rotation":0,
                 "type":"wall",
                 "visible":true,
                 "width":28,
                 "x":355.333333333333,
                 "y":130
                }, 
                {
                 "height":28,
                 "id":13,
                 "name":"",
                 "rotation":0,
                 "type":"wall",
                 "visible":true,
                 "width":28,
                 "x":393.532881282962,
                 "y":211.041806971416
                }, 
                {
                 "height":28,
                 "id":14,
                 "name":"",
                 "rotation":0,
                 "type":"wall",
                 "visible":true,
                 "width":28,
                 "x":155.857404246814,
                 "y":60.4813567661482
                }, 
                {
                 "height":28,
                 "id":15,
                 "name":"",
                 "rotation":0,
                 "type":"wall",
                 "visible":true,
                 "width":28,
                 "x":465.523163737565,
                 "y":15.7511877854144
                }, 
                {
                 "height":28,
                 "id":20,
                 "name":"",
                 "rotation":0,
                 "type":"wall",
                 "visible":true,
                 "width":28,
                 "x":284.820794317081,
                 "y":384.403616402971
                }, 
                {
                 "height":47.4842935559759,
                 "id":21,
                 "name":"",
                 "rotation":0,
                 "type":"wall",
                 "visible":true,
                 "width":40.3990958992573,
                 "x":472.578532220121,
                 "y":351.508249150483
                }, 
                {
                 "height":28,
                 "id":22,
                 "name":"",
                 "rotation":0,
                 "type":"wall",
                 "visible":true,
                 "width":28,
                 "x":563.050847978843,
                 "y":393.494011101373
                }, 
                {
                 "gid":1,
                 "height":64,
                 "id":25,
                 "name":"",
                 "rotation":0,
                 "type":"hero",
                 "visible":true,
                 "width":64,
                 "x":84.0271230222795,
                 "y":207.397512185372
                }, 
                {
                 "gid":321,
                 "height":64,
                 "id":60,
                 "name":"",
                 "rotation":0,
                 "type":"zombie",
                 "visible":true,
                 "width":64,
                 "x":386.666666666667,
                 "y":381.333333333333
                }, 
                {
                 "gid":418,
                 "height":24,
                 "id":78,
                 "name":"",
                 "rotation":0,
                 "type":"testTube",
                 "visible":true,
                 "width":24,
                 "x":605.743499853929,
                 "y":440.614911511909
                }, 
                {
                 "gid":418,
                 "height":24,
                 "id":79,
                 "name":"",
                 "rotation":0,
                 "type":"testTube",
                 "visible":true,
                 "width":24,
                 "x":556.780786321633,
                 "y":384.488583421745
                }, 
                {
                 "height":510.813106385596,
                 "id":84,
                 "name":"",
                 "rotation":0,
                 "type":"lava",
                 "visible":true,
                 "width":32,
                 "x":673.818534065224,
                 "y":59.9760444054922
                }, 
                {
                 "gid":418,
                 "height":24,
                 "id":91,
                 "name":"",
                 "rotation":0,
                 "type":"testTube",
                 "visible":true,
                 "width":24,
                 "x":443.223949444163,
                 "y":326.318188108308
                }, 
                {
                 "gid":321,
                 "height":64,
                 "id":95,
                 "name":"",
                 "rotation":0,
                 "type":"zombie",
                 "visible":true,
                 "width":64,
                 "x":166.385534388118,
                 "y":442.708243000139
                }, 
                {
                 "gid":321,
                 "height":64,
                 "id":96,
                 "name":"",
                 "rotation":0,
                 "type":"zombie",
                 "visible":true,
                 "width":64,
                 "x":359.457170533696,
                 "y":117.674800498178
                }, 
                {
                 "gid":418,
                 "height":24,
                 "id":97,
                 "name":"",
                 "rotation":0,
                 "type":"testTube",
                 "visible":true,
                 "width":24,
                 "x":676.149822408783,
                 "y":41.1389824253886
                }, 
                {
                 "gid":418,
                 "height":24,
                 "id":98,
                 "name":"",
                 "rotation":0,
                 "type":"testTube",
                 "visible":true,
                 "width":24,
                 "x":1041.92315143687,
                 "y":348.459430785553
                }, 
                {
                 "height":25.3430573227548,
                 "id":99,
                 "name":"",
                 "properties":[
                        {
                         "name":"toY",
                         "type":"int",
                         "value":63
                        }],
                 "rotation":0,
                 "type":"wall",
                 "visible":true,
                 "width":40.3991,
                 "x":622.782137347202,
                 "y":344.688128149361
                }, 
                {
                 "gid":420,
                 "height":40,
                 "id":100,
                 "name":"",
                 "rotation":0,
                 "type":"virus",
                 "visible":true,
                 "width":40,
                 "x":279.349600996356,
                 "y":257.354121500069
                }, 
                {
                 "gid":420,
                 "height":40,
                 "id":101,
                 "name":"",
                 "rotation":0,
                 "type":"virus",
                 "visible":true,
                 "width":40,
                 "x":608.811292033766,
                 "y":144.730845518705
                }, 
                {
                 "gid":420,
                 "height":40,
                 "id":102,
                 "name":"",
                 "rotation":0,
                 "type":"virus",
                 "visible":true,
                 "width":40,
                 "x":781.512984916279,
                 "y":434.338299737073
                }, 
                {
                 "gid":420,
                 "height":40,
                 "id":103,
                 "name":"",
                 "rotation":0,
                 "type":"virus",
                 "visible":true,
                 "width":40,
                 "x":785.055583744638,
                 "y":362.600673462798
                }, 
                {
                 "gid":421,
                 "height":89,
                 "id":104,
                 "name":"",
                 "rotation":0,
                 "type":"table",
                 "visible":true,
                 "width":83,
                 "x":213.181465934776,
                 "y":269.840675307902
                }, 
                {
                 "height":28,
                 "id":107,
                 "name":"",
                 "rotation":0,
                 "type":"wall",
                 "visible":true,
                 "width":28,
                 "x":1040.80880114396,
                 "y":386.313667604594
                }, 
                {
                 "height":41.2847,
                 "id":109,
                 "name":"",
                 "rotation":0,
                 "type":"lava",
                 "visible":true,
                 "width":221.233299091286,
                 "x":934.007179966789,
                 "y":447.86634505051
                }, 
                {
                 "height":35.0851976567185,
                 "id":110,
                 "name":"",
                 "rotation":0,
                 "type":"wall",
                 "visible":true,
                 "width":162.618755477651,
                 "x":709.575810692375,
                 "y":463.365192121408
                }],
         "opacity":1,
         "type":"objectgroup",
         "visible":true,
         "x":0,
         "y":0
        }],
 "nextlayerid":3,
 "nextobjectid":111,
 "orientation":"orthogonal",
 "renderorder":"right-down",
 "tiledversion":"1.3.3",
 "tileheight":32,
 "tilesets":[
        {
         "columns":16,
         "firstgid":1,
         "image":"..\/res\/sprite\/cat.png",
         "imageheight":1024,
         "imagewidth":1024,
         "margin":0,
         "name":"cat",
         "spacing":0,
         "tilecount":256,
         "tileheight":64,
         "tiles":[
                {
                 "id":0,
                 "objectgroup":
                    {
                     "draworder":"index",
                     "name":"",
                     "objects":[
                            {
                             "height":28.7640449438202,
                             "id":1,
                             "name":"",
                             "rotation":0,
                             "type":"",
                             "visible":true,
                             "width":16,
                             "x":23.6546422235364,
                             "y":25.357776463631
                            }],
                     "opacity":1,
                     "type":"objectgroup",
                     "visible":true,
                     "x":0,
                     "y":0
                    }
                }],
         "tilewidth":64
        }, 
        {
         "columns":8,
         "firstgid":257,
         "image":"..\/res\/sprite\/monster1.png",
         "imageheight":512,
         "imagewidth":512,
         "margin":0,
         "name":"monster1",
         "spacing":0,
         "tilecount":64,
         "tileheight":64,
         "tiles":[
                {
                 "id":0,
                 "objectgroup":
                    {
                     "draworder":"index",
                     "name":"",
                     "objects":[
                            {
                             "height":24.6008279124778,
                             "id":1,
                             "name":"",
                             "rotation":0,
                             "type":"",
                             "visible":true,
                             "width":22.5192193968066,
                             "x":19.3021880544057,
                             "y":29.3317563571851
                            }],
                     "opacity":1,
                     "type":"objectgroup",
                     "visible":true,
                     "x":0,
                     "y":0
                    }
                }],
         "tilewidth":64
        }, 
        {
         "columns":8,
         "firstgid":321,
         "image":"..\/res\/sprite\/zombie.png",
         "imageheight":512,
         "imagewidth":512,
         "margin":0,
         "name":"skeleton",
         "spacing":0,
         "tilecount":64,
         "tileheight":64,
         "tiles":[
                {
                 "id":0,
                 "objectgroup":
                    {
                     "draworder":"index",
                     "name":"",
                     "objects":[
                            {
                             "height":40.4967474866943,
                             "id":2,
                             "name":"",
                             "rotation":0,
                             "type":"",
                             "visible":true,
                             "width":20.4376108811354,
                             "x":21.9515079834418,
                             "y":19.8698994677706
                            }],
                     "opacity":1,
                     "type":"objectgroup",
                     "visible":true,
                     "x":0,
                     "y":0
                    }
                }],
         "tilewidth":64
        }, 
        {
         "columns":8,
         "firstgid":385,
         "image":"..\/res\/sprite\/monster2.png",
         "imageheight":256,
         "imagewidth":512,
         "margin":0,
         "name":"monster2",
         "spacing":0,
         "tilecount":32,
         "tileheight":64,
         "tiles":[
                {
                 "id":9,
                 "objectgroup":
                    {
                     "draworder":"index",
                     "name":"",
                     "objects":[
                            {
                             "height":37.4689532820816,
                             "id":3,
                             "name":"",
                             "rotation":0,
                             "type":"",
                             "visible":true,
                             "width":26.8716735659373,
                             "x":18.3560023654642,
                             "y":18.5452395032525
                            }],
                     "opacity":1,
                     "type":"objectgroup",
                     "visible":true,
                     "x":0,
                     "y":0
                    }
                }],
         "tilewidth":64
        }, 
        {
         "columns":1,
         "firstgid":417,
         "image":"..\/res\/sprite\/bloodDrop.png",
         "imageheight":16,
         "imagewidth":16,
         "margin":0,
         "name":"bloodDrop",
         "spacing":0,
         "tilecount":1,
         "tileheight":16,
         "tilewidth":16
        }, 
        {
         "columns":1,
         "firstgid":418,
         "image":"..\/res\/sprite\/testTube.png",
         "imageheight":24,
         "imagewidth":24,
         "margin":0,
         "name":"testTube",
         "spacing":0,
         "tilecount":1,
         "tileheight":24,
         "tilewidth":24
        }, 
        {
         "columns":1,
         "firstgid":419,
         "image":"..\/res\/sprite\/tree.png",
         "imageheight":157,
         "imagewidth":100,
         "margin":0,
         "name":"tree",
         "spacing":0,
         "tilecount":1,
         "tileheight":157,
         "tilewidth":100
        }, 
        {
         "columns":1,
         "firstgid":420,
         "image":"..\/res\/sprite\/virus.png",
         "imageheight":40,
         "imagewidth":40,
         "margin":0,
         "name":"virus",
         "spacing":0,
         "tilecount":1,
         "tileheight":40,
         "tilewidth":40
        }, 
        {
         "columns":1,
         "firstgid":421,
         "image":"..\/res\/sprite\/table.png",
         "imageheight":89,
         "imagewidth":83,
         "margin":0,
         "name":"table",
         "spacing":0,
         "tilecount":1,
         "tileheight":89,
         "tilewidth":83
        }, 
        {
         "columns":1,
         "firstgid":422,
         "image":"..\/res\/sprite\/ironCar.png",
         "imageheight":46,
         "imagewidth":100,
         "margin":0,
         "name":"ironCar",
         "spacing":0,
         "tilecount":1,
         "tileheight":46,
         "tilewidth":100
        }],
 "tilewidth":32,
 "type":"map",
 "version":1.2,
 "width":35
}